choose-0.1.dist-info/DESCRIPTION.rst
choose-0.1.dist-info/METADATA
choose-0.1.dist-info/RECORD
choose-0.1.dist-info/WHEEL
choose-0.1.dist-info/metadata.json
choose-0.1.dist-info/top_level.txt
tests/__init__.py
tests/test_choose.py
